dobles/__init__.py
dobles/allowance.py
dobles/call_count_accumulator.py
dobles/class_double.py
dobles/exceptions.py
dobles/expectation.py
dobles/instance_double.py
dobles/lifecycle.py
dobles/method_double.py
dobles/object_double.py
dobles/patch.py
dobles/proxy.py
dobles/proxy_method.py
dobles/proxy_property.py
dobles/pytest_plugin.py
dobles/space.py
dobles/target.py
dobles/targets/__init__.py
dobles/targets/allowance_target.py
dobles/targets/expectation_target.py
dobles/targets/patch_target.py
dobles/testing.py
dobles/unittest.py
dobles/utils.py
dobles/verification.py
dobles-4.0.2.dist-info/LICENSE
dobles-4.0.2.dist-info/METADATA
dobles-4.0.2.dist-info/WHEEL
dobles-4.0.2.dist-info/entry_points.txt
dobles-4.0.2.dist-info/RECORD
