Metadata-Version: 2.1
Name: dobles
Version: 4.0.2
Summary: Test dobles for Python.
Home-page: https://github.com/smartfastlabs/dobles
License: MIT
Keywords: testing,test dobles,mocks,mocking,stubs,stubbing
Author: Jimmy Cuadra
Author-email: jimmy@uber.com
Maintainer: Todd Sifleet
Maintainer-email: todd@smartfast.com
Requires-Python: >=3.9,<4.0
Classifier: Development Status :: 1 - Planning
Classifier: Intended Audience :: Developers
Classifier: License :: OSI Approved :: MIT License
Classifier: Programming Language :: Python
Classifier: Programming Language :: Python :: 3
Classifier: Programming Language :: Python :: 3.9
Classifier: Programming Language :: Python :: 3.10
Classifier: Programming Language :: Python :: 3.11
Classifier: Programming Language :: Python :: 3.12
Classifier: Programming Language :: Python :: 3.8
Classifier: Topic :: Software Development :: Testing
Project-URL: Repository, https://github.com/smartfastlabs/dobles
